httplocust/__about__.py
httplocust/__init__.py
httplocust/cli.py
httplocust/locusts.py
httplocust/task.py
httplocust/template/locustfile_template
rtsf_locust-1.1.1.dist-info/METADATA
rtsf_locust-1.1.1.dist-info/RECORD
rtsf_locust-1.1.1.dist-info/WHEEL
rtsf_locust-1.1.1.dist-info/entry_points.txt
rtsf_locust-1.1.1.dist-info/top_level.txt
