Metadata-Version: 2.1
Name: rtsf-locust
Version: 1.1.1
Summary: http(s) load testing, base on locust and rtsf-http
Home-page: https://github.com/RockFeng0/rtsf-locust
Author: 罗科峰
Author-email: lkf20031988@163.com
License: MIT
Keywords: test http api https
Platform: UNKNOWN
Requires-Python: >=2.7, !=3.0.*, !=3.1.*, !=3.2.*, !=3.3.*, <4
Requires-Dist: locust
Requires-Dist: rtsf-http
